pandas_checks/DataFrameChecks.py
pandas_checks/SeriesChecks.py
pandas_checks/__init__.py
pandas_checks/display.py
pandas_checks/options.py
pandas_checks/run_checks.py
pandas_checks/timer.py
pandas_checks/utils.py
pandas_checks-1.1.0.dist-info/LICENSE
pandas_checks-1.1.0.dist-info/METADATA
pandas_checks-1.1.0.dist-info/WHEEL
pandas_checks-1.1.0.dist-info/RECORD
