Metadata-Version: 2.3
Name: pandas-checks
Version: 1.1.0
Summary: Non-invasive health checks for Pandas method chains
License: BSD-3-Clause
Keywords: pandas,method chains,data science,data engineering
Author: Chad Parmet
Author-email: cparmet@gmail.com
Requires-Python: >=3.9
Classifier: License :: OSI Approved :: BSD License
Classifier: Programming Language :: Python :: 3
Classifier: Programming Language :: Python :: 3.9
Classifier: Programming Language :: Python :: 3.10
Classifier: Programming Language :: Python :: 3.11
Classifier: Programming Language :: Python :: 3.12
Classifier: Programming Language :: Python :: 3.13
Requires-Dist: Jinja2 (>=3.1.4)
Requires-Dist: emoji (>=2.12.1)
Requires-Dist: ipython (>=7.23.1)
Requires-Dist: matplotlib (>=3.5.3)
Requires-Dist: pandas (>=1.4,<3.0)
Requires-Dist: termcolor (>=2.3.0)
Requires-Dist: tornado (>=6.5.0)
Project-URL: Documentation, https://cparmet.github.io/pandas-checks/
Project-URL: Repository, https://github.com/cparmet/pandas-checks
Project-URL: issues, https://github.com/cparmet/pandas-checks/issues
